kaldi_active_grammar/LICENSE.txt
kaldi_active_grammar/__init__.py
kaldi_active_grammar/__main__.py
kaldi_active_grammar/compiler.py
kaldi_active_grammar/defaults.py
kaldi_active_grammar/ffi.py
kaldi_active_grammar/model.py
kaldi_active_grammar/plain_dictation.py
kaldi_active_grammar/utils.py
kaldi_active_grammar/wfst.py
kaldi_active_grammar/wrapper.py
kaldi_active_grammar/exec/windows/kaldi-dragonfly.dll
kaldi_active_grammar/kaldi/__init__.py
kaldi_active_grammar/kaldi/augment_phones_txt.py
kaldi_active_grammar/kaldi/augment_phones_txt_py2.py
kaldi_active_grammar/kaldi/augment_words_txt.py
kaldi_active_grammar/kaldi/augment_words_txt_py2.py
kaldi_active_grammar/kaldi/make_lexicon_fst.py
kaldi_active_grammar/kaldi/make_lexicon_fst_py2.py
kaldi_active_grammar-3.1.0.dist-info/LICENSE.txt
kaldi_active_grammar-3.1.0.dist-info/METADATA
kaldi_active_grammar-3.1.0.dist-info/WHEEL
kaldi_active_grammar-3.1.0.dist-info/top_level.txt
kaldi_active_grammar-3.1.0.dist-info/RECORD
