Metadata-Version: 2.1
Name: kaldi-active-grammar
Version: 3.1.0
Summary: Kaldi speech recognition with grammars that can be set active/inactive dynamically at decode-time
Home-page: https://github.com/daanzu/kaldi-active-grammar
Author: David Zurow
Author-email: daanzu@gmail.com
License: AGPL-3.0
Project-URL: Bug Reports, https://github.com/daanzu/kaldi-active-grammar/issues
Project-URL: Funding, https://github.com/sponsors/daanzu
Project-URL: Source, https://github.com/daanzu/kaldi-active-grammar/
Keywords: kaldi speech recognition grammar dragonfly
Platform: UNKNOWN
Classifier: Development Status :: 5 - Production/Stable
Classifier: Intended Audience :: Developers
Classifier: License :: OSI Approved :: GNU Affero General Public License v3
Classifier: Programming Language :: Python :: 3
Classifier: Programming Language :: Python :: 3.6
Classifier: Programming Language :: Python :: 3.7
Classifier: Programming Language :: Python :: 3.8
Classifier: Programming Language :: Python :: 3.9
Requires-Python: >=2.7, !=3.0.*, !=3.1.*, !=3.2.*, !=3.3.*, <4
License-File: LICENSE.txt
Requires-Dist: cffi (~=1.12)
Requires-Dist: numpy (!=1.19.4,~=1.16)
Requires-Dist: ush (~=3.1)
Requires-Dist: six
Requires-Dist: futures ; python_version == "2.7"
Provides-Extra: g2p_en
Requires-Dist: g2p-en (~=2.1.0) ; extra == 'g2p_en'
Provides-Extra: online
Requires-Dist: requests (~=2.18) ; extra == 'online'
